sphinx_interrogatedb/__init__.py
sphinx_interrogatedb/documenters.py
sphinx_interrogatedb/idb.py
sphinx_interrogatedb-2.0.1.dist-info/METADATA
sphinx_interrogatedb-2.0.1.dist-info/WHEEL
sphinx_interrogatedb-2.0.1.dist-info/top_level.txt
sphinx_interrogatedb-2.0.1.dist-info/RECORD
