Metadata-Version: 2.1
Name: sphinx-interrogatedb
Version: 2.0.1
Summary: Sphinx extension to enhance autodoc for interrogated modules
Home-page: https://github.com/panda3d/sphinx-interrogatedb
Author: rdb
Author-email: me@rdb.name
License: Modified BSD License
Classifier: Programming Language :: Python :: 3
Classifier: Operating System :: OS Independent
Classifier: Framework :: Sphinx
Classifier: Topic :: Documentation
Classifier: Topic :: Software Development :: Documentation
Classifier: License :: OSI Approved :: BSD License
Requires-Dist: sphinx >=2.2.0
Requires-Dist: panda3d-interrogate
